sandbox/__main__.py
sandbox/Core/ExecuteParentShell.py
sandbox/Core/FzfHandler.py
sandbox/Core/IEnvironment.py
sandbox/Core/IPipeline.py
sandbox/Core/RegisterEnvironment.py
sandbox/Core/RegisterPipeline.py
sandbox/Environments/ConfigurableEnvironment.py
sandbox/Pipelines/Execute.py
sandbox/Pipelines/Open.py
sandbox/Pipelines/Reset.py
sandbox/Pipelines/Save.py
ideas_sandbox-0.0.2.dist-info/LICENSE.txt
ideas_sandbox-0.0.2.dist-info/METADATA
ideas_sandbox-0.0.2.dist-info/WHEEL
ideas_sandbox-0.0.2.dist-info/entry_points.txt
ideas_sandbox-0.0.2.dist-info/top_level.txt
ideas_sandbox-0.0.2.dist-info/RECORD
