Metadata-Version: 2.1
Name: ideas-sandbox
Version: 0.0.2
Summary: sandbox framework
Author-email: dcoello-dev <dcpulido91@gmail.com>
License: M.IT License
Project-URL: Repository, https://github.com/dcoello-dev/ideas-sandbox
Keywords: notes,tool,cli,framework,sandbox
Classifier: Development Status :: 3 - Alpha
Classifier: Intended Audience :: Developers
Classifier: Programming Language :: Python :: 3
Classifier: License :: OSI Approved :: MIT License
Classifier: Operating System :: OS Independent
Requires-Python: >=3.8
License-File: LICENSE.txt
Requires-Dist: pyfzf
Requires-Dist: toml
Provides-Extra: tests
Requires-Dist: pytest-mock ==3.14.0 ; extra == 'tests'
